README.md
setup.py
pitchperception/__init__.py
pitchperception/_version.py
pitchperception/pitchperception.py
pitchperception.egg-info/PKG-INFO
pitchperception.egg-info/SOURCES.txt
pitchperception.egg-info/dependency_links.txt
pitchperception.egg-info/entry_points.txt
pitchperception.egg-info/top_level.txt