Metadata-Version: 1.0
Name: pitchperception
Version: 2020.6.20.1
Summary: An interactive game to test the user's pitch perception abilities.
Home-page: https://github.com/erjoalgo/pitchperception
Author: Ernesto Alfonso
Author-email: erjoalgo@gmail.com
License: GPLv3
Platform: UNKNOWN
